remove_duplicates/__init__.py
remove_duplicates/internationalization.py
remove_duplicates/my_utils.py
remove_duplicates/remove_dup.py
remove_duplicates/str_with_trans.py
remove_duplicates/translated.csv
remove_duplicates-1.0.5.dist-info/LICENSE.md
remove_duplicates-1.0.5.dist-info/METADATA
remove_duplicates-1.0.5.dist-info/WHEEL
remove_duplicates-1.0.5.dist-info/entry_points.txt
remove_duplicates-1.0.5.dist-info/top_level.txt
remove_duplicates-1.0.5.dist-info/RECORD
