Metadata-Version: 2.1
Name: remove-duplicates
Version: 1.0.5
Summary: Utility to recursive search and move/delete duplicate files of the same size and context in specified folder.
Home-page: https://github.com/octaprog7/remove_duplicates
Author: Roman Shevchik
Author-email: goctaprog@gmail.com
License: UNKNOWN
Platform: UNKNOWN
Classifier: Programming Language :: Python :: 3
Classifier: License :: OSI Approved :: MIT License
Classifier: Operating System :: OS Independent
Classifier: Development Status :: 5 - Production/Stable
Classifier: Environment :: Console
Classifier: Intended Audience :: End Users/Desktop
Classifier: Intended Audience :: Developers
Classifier: Intended Audience :: System Administrators
Requires-Python: >=3.7.2,<3.12
License-File: LICENSE.md
